[
    {
        "title": "Python developer - ötudent",
        "place": "Slovensko",
        "salary": "6 Ä / hodina",
        "contract_type": "dohoda o brig. pr·ci ötudenta",
        "contact_email": "hr@hyperia.sk"
    },
    {
        "title": "Senior PPC öpecialista",
        "place": "Slovensko",
        "salary": "od 1 800,- Ä",
        "contract_type": "TPP, ûivnosù",
        "contact_email": "hr@hyperia.sk"
    },
    {
        "title": "Product owner",
        "place": "Slovensko",
        "salary": "od 2 000 ,- Ä",
        "contract_type": "TPP, ûivnosù",
        "contact_email": "hr@hyperia.sk"
    },
    {
        "title": "Lead Frontend developer",
        "place": "Slovensko",
        "salary": "2 000 - 4 000 ,- Ä( Suma pri ûivnosti na z·klade sk˙senostÌ uch·dzaËa )",
        "contract_type": "TPP, ûivnosù",
        "contact_email": "hr@hyperia.sk"
    },
    {
        "title": "Frontend developer (medior/senior)",
        "place": "Slovensko",
        "salary": "2 000 - 4 000 ,- Ä( Suma pri ûivnosti na z·klade sk˙senostÌ uch·dzaËa )",
        "contract_type": "TPP, ûivnosù",
        "contact_email": "hr@hyperia.sk"
    },
    {
        "title": "Kimbino senior PHP developer",
        "place": "Slovensko",
        "salary": "od 2 000 ,- Ä",
        "contract_type": "TPP, ûivnosù",
        "contact_email": "hr@hyperia.sk"
    }
]